ca_api_wrapper/api/__init__.py
ca_api_wrapper/api/client.py
ca_api_wrapper/api/client_registry.py
ca_api_wrapper/api/exports.py
ca_api_wrapper/api/filters.py
ca_api_wrapper/api/orders.py
ca_api_wrapper/api/products.py
ca_api_wrapper/custom_models/index.py
ca_api_wrapper/custom_models/orders/Order.py
ca_api_wrapper/custom_models/orders/OrderItem.py
ca_api_wrapper/custom_models/orders/PaymentStatus.py
ca_api_wrapper/custom_models/orders/Promotions.py
ca_api_wrapper/tests.py
ca_api_wrapper-2.0.9.dist-info/WHEEL
ca_api_wrapper-2.0.9.dist-info/METADATA
ca_api_wrapper-2.0.9.dist-info/RECORD
