Metadata-Version: 2.1
Name: ca-api-wrapper
Version: 2.0.9
Summary: 
Author: Vick Mu
Author-email: arbi3400@gmail.com
Requires-Python: >=3.10,<4.0
Classifier: Programming Language :: Python :: 3
Classifier: Programming Language :: Python :: 3.10
Requires-Dist: pandas (>=2.2.1,<3.0.0)
Requires-Dist: requests (>=2.31.0,<3.0.0)
